qlik_test_moshe/__init__.py
qlik_test_moshe-0.1.0.dist-info/METADATA
qlik_test_moshe-0.1.0.dist-info/WHEEL
qlik_test_moshe-0.1.0.dist-info/RECORD
